{
	"description": "项目配置文件。",
	"setting": {
		"urlCheck": false,
		"es6": true,
		"postcss": false,
		"minified": true,
		"newFeature": true
	},
	"compileType": "miniprogram",
	"libVersion": "2.3.2",
	"appid": "wx36410b03870f2336",
	"projectname": "%E5%B0%8F%E8%A7%85%E6%99%BA%E8%83%BD%E6%A5%BC%E5%AE%87%E6%9C%8D%E5%8A%A1%E6%B5%8B%E8%AF%95",
	"scripts": {},
	"condition": {
		"search": {
			"current": -1,
			"list": []
		},
		"conversation": {
			"current": -1,
			"list": []
		},
		"plugin": {
			"current": -1,
			"list": []
		},
		"game": {
			"current": -1,
			"list": []
		},
		"miniprogram": {
			"current": 9,
			"list": [
				{
					"id": 0,
					"name": "申请发卡",
					"pathName": "pages/invite-apply/invite-apply",
					"query": "scene=17_234324",
					"scene": "1011"
				},
				{
					"id": 1,
					"name": "接受邀请",
					"pathName": "pages/invite-receive/invite-receive",
					"query": "invitation_id=265",
					"scene": "1044"
				},
				{
					"id": 2,
					"name": "员工快捷取卡",
					"pathName": "pages/employee/take-card/guide/index",
					"query": "company_id=17",
					"scene": "1044"
				},
				{
					"id": -1,
					"name": "管理",
					"pathName": "pages/manage/manage",
					"query": "",
					"scene": "1044"
				},
				{
					"id": -1,
					"name": "邀请",
					"pathName": "pages/invite/invite",
					"query": "",
					"scene": "1044"
				},
				{
					"id": 5,
					"name": "申请结果",
					"pathName": "pages/invite-apply-result/invite-apply-result",
					"query": "visit_apply_id=96",
					"scene": "1044"
				},
				{
					"id": 6,
					"name": "录入人脸",
					"pathName": "pages/collect-info/face/index",
					"query": "company_id=17",
					"scene": "1044"
				},
				{
					"id": -1,
					"name": "小觅VIP卡",
					"pathName": "page/benifit/pages/vip-card/vip-card",
					"query": "",
					"scene": "1011"
				},
				{
					"id": -1,
					"name": "商城首页",
					"pathName": "page/benifit/pages/mall-home/mall-home",
					"query": ""
				},
				{
					"id": 9,
					"name": "邀请员工",
					"pathName": "pages/employee/invite-staff/index",
					"query": "commerce_id=6",
					"scene": "1044"
				},
				{
					"id": -1,
					"name": "ifontdemo",
					"pathName": "pages/demo/iconfont/index",
					"query": "",
					"scene": "1011"
				},
				{
					"id": 12,
					"name": "首页",
					"pathName": "pages/manage/manage",
					"query": ""
				},
				{
					"id": 13,
					"name": "上传视频",
					"pathName": "pages/create-company/updateReviewInfo/index",
					"query": ""
				},
				{
					"id": 14,
					"name": "确定公司信息",
					"pathName": "pages/employee/join-company/confirmCompanyInformation/index",
					"query": "company_code=GERW1XWQ"
				}
			]
		}
	}
}